photorec_sorter/__init__.py
photorec_sorter/__main__.py
photorec_sorter/cli.py
photorec_sorter/files_per_folder_limiter.py
photorec_sorter/jpg_sorter.py
photorec_sorter/recovery.py
photorec_sorter-0.2.2.dist-info/METADATA
photorec_sorter-0.2.2.dist-info/WHEEL
photorec_sorter-0.2.2.dist-info/entry_points.txt
photorec_sorter-0.2.2.dist-info/licenses/LICENSE
photorec_sorter-0.2.2.dist-info/RECORD
