Metadata-Version: 2.4
Name: photorec-sorter
Version: 0.2.2
Summary: A tool to sort/organize files recovered by the PhotoRec tool
Project-URL: Homepage, https://github.com/RecRanger/photorec-sorter
Project-URL: Issues, https://github.com/RecRanger/photorec-sorter/issues
Author-email: RecRanger <RecRanger+package@proton.me>
License-File: LICENSE
Classifier: License :: OSI Approved :: The Unlicense (Unlicense)
Classifier: Operating System :: OS Independent
Classifier: Programming Language :: Python :: 3
Requires-Python: >=3.10
Requires-Dist: exifread
Requires-Dist: loguru
